django_unfold_admin_list_filter_dropdown-1.0.12.dist-info/licenses/LICENSE
django_unfold_admin_listfilter_dropdown/__init__.py
django_unfold_admin_listfilter_dropdown/filters.py
django_unfold_admin_listfilter_dropdown/templates/django_unfold_admin_listfilter_dropdown/dropdown_filter.html
django_unfold_admin_list_filter_dropdown-1.0.12.dist-info/METADATA
django_unfold_admin_list_filter_dropdown-1.0.12.dist-info/WHEEL
django_unfold_admin_list_filter_dropdown-1.0.12.dist-info/top_level.txt
django_unfold_admin_list_filter_dropdown-1.0.12.dist-info/RECORD
