Metadata-Version: 2.4
Name: django-unfold-admin-list-filter-dropdown
Version: 1.0.12
Summary: Use dropdowns in Django admin list filter
Home-page: https://github.com/francoborrelli/django-unfold-admin-list-filter-dropdown
Download-URL: https://github.com/francoborrelli/django-unfold-admin-list-filter-dropdow/archive/1.0.12.zip
Author: Franco Borrelli
Author-email: francoborrelli96@gmail.com
License: MIT License
Keywords: django,admin,filter,dropdown,unfold,django-unfold
Classifier: Environment :: Web Environment
Classifier: Framework :: Django
Classifier: Intended Audience :: Developers
Classifier: License :: OSI Approved :: MIT License
Classifier: Operating System :: OS Independent
Classifier: Programming Language :: Python
Classifier: Topic :: Internet :: WWW/HTTP
Classifier: Topic :: Internet :: WWW/HTTP :: Dynamic Content
License-File: LICENSE
Dynamic: author
Dynamic: author-email
Dynamic: classifier
Dynamic: description
Dynamic: description-content-type
Dynamic: download-url
Dynamic: home-page
Dynamic: keywords
Dynamic: license
Dynamic: license-file
Dynamic: summary
